inrcot/__init__.py
inrcot/classes.py
inrcot/commands.py
inrcot/constants.py
inrcot/functions.py
inrcot-5.2.0.dist-info/LICENSE
inrcot-5.2.0.dist-info/METADATA
inrcot-5.2.0.dist-info/WHEEL
inrcot-5.2.0.dist-info/entry_points.txt
inrcot-5.2.0.dist-info/top_level.txt
inrcot-5.2.0.dist-info/RECORD
