Metadata-Version: 2.1
Name: inrcot
Version: 5.2.0
Summary: inReach Cursor on Target Gateway.
Home-page: https://github.com/ampledata/inrcot
Author: Greg Albrecht
Author-email: oss@undef.net
License: Apache License, Version 2.0
Keywords: Satellite,SAR,Search and Rescue,Cursor on Target,ATAK,TAK,CoT,WinTAK,iTAK,TAK Server
Classifier: Programming Language :: Python :: 3
Classifier: License :: OSI Approved :: Apache Software License
Classifier: Operating System :: OS Independent
License-File: LICENSE
Requires-Dist: pytak (>=5.6.1)
Requires-Dist: aiohttp
